README.md
setup.cfg
setup.py
duxwrap/__init__.py
duxwrap/duxwrap.py
duxwrap.egg-info/PKG-INFO
duxwrap.egg-info/SOURCES.txt
duxwrap.egg-info/dependency_links.txt
duxwrap.egg-info/requires.txt
duxwrap.egg-info/top_level.txt