Metadata-Version: 2.1
Name: duxwrap
Version: 0.6
Summary: Dux-Soup remote control API wrapper
Home-page: https://github.com/abrihter/duxwrap/releases
Author: bojan
Author-email: 
License: MIT
Download-URL: https://github.com/abrihter/duxwrap/archive/v_06.tar.gz
Keywords: DUX SOUP,API,WRAPPER
Platform: UNKNOWN
Classifier: Development Status :: 5 - Production/Stable
Classifier: Intended Audience :: Developers
Classifier: Topic :: Software Development :: Build Tools
Classifier: License :: OSI Approved :: MIT License
Classifier: Programming Language :: Python :: 3
